coffifilter/__init__.py
coffifilter/client.py
coffifilter/decorators.py
coffifilter/helpers.py
coffifilter/py.typed
coffifilter-0.0.1.dist-info/LICENSE
coffifilter-0.0.1.dist-info/METADATA
coffifilter-0.0.1.dist-info/WHEEL
coffifilter-0.0.1.dist-info/entry_points.txt
coffifilter-0.0.1.dist-info/RECORD
