Metadata-Version: 2.1
Name: coffifilter
Version: 0.0.1
Summary: CoffiFilter
Home-page: https://github.com/sjakati98/coffifilter
License: GPL-3.0
Author: Shishir Jakati
Author-email: shishir.jakati98@gmail.com
Requires-Python: >=3.7,<4.0
Classifier: Development Status :: 2 - Pre-Alpha
Classifier: License :: OSI Approved :: GNU General Public License v3 (GPLv3)
Classifier: Programming Language :: Python :: 3
Classifier: Programming Language :: Python :: 3.7
Classifier: Programming Language :: Python :: 3.8
Classifier: Programming Language :: Python :: 3.9
Classifier: Programming Language :: Python :: 3.10
Classifier: Programming Language :: Python :: 3.11
Classifier: Programming Language :: Python :: 3.12
Requires-Dist: click (>=8.0.1)
Requires-Dist: pyyaml (>=6.0.1,<7.0.0)
Requires-Dist: redis (>=5.0.4,<6.0.0)
Project-URL: Changelog, https://github.com/sjakati98/coffifilter/releases
Project-URL: Documentation, https://coffifilter.readthedocs.io
Project-URL: Repository, https://github.com/sjakati98/coffifilter
